vanguardkit/__init__.py
vanguardkit/html_distance.py
vanguardkit/html_tree.py
vanguardkit/vanguard_node.py
vanguardkit-0.2.0.dist-info/LICENSE
vanguardkit-0.2.0.dist-info/WHEEL
vanguardkit-0.2.0.dist-info/METADATA
vanguardkit-0.2.0.dist-info/RECORD
