Metadata-Version: 2.1
Name: vanguardkit
Version: 0.2.0
Summary: A convenient way to calculate the edit distance between html files
License: MIT
Author: Daniel Omar Vergara Pérez
Author-email: daniel.omar.vergara@gmail.com
Requires-Python: >=3.7,<4.0
Classifier: License :: OSI Approved :: MIT License
Classifier: Programming Language :: Python :: 3
Classifier: Programming Language :: Python :: 3.6
Classifier: Programming Language :: Python :: 3.7
Classifier: Programming Language :: Python :: 3.8
Classifier: Programming Language :: Python :: Implementation :: CPython
Classifier: Programming Language :: Python :: Implementation :: PyPy
Requires-Dist: beautifulsoup4 (>=4.9.0,<5.0.0)
Requires-Dist: html5lib (>=1.0.1,<2.0.0)
Requires-Dist: zss (>=1.2.0,<2.0.0)
